pyparrot/Bebop.py
pyparrot/DroneVision.py
pyparrot/DroneVisionGUI.py
pyparrot/Minidrone.py
pyparrot/VisionServer.py
pyparrot/__init__.py
pyparrot/commandsandsensors/DroneCommandParser.py
pyparrot/commandsandsensors/DroneSensorParser.py
pyparrot/commandsandsensors/__init__.py
pyparrot/commandsandsensors/ardrone3.xml
pyparrot/commandsandsensors/common.xml
pyparrot/commandsandsensors/followme.xml
pyparrot/commandsandsensors/generic.xml
pyparrot/commandsandsensors/minidrone.xml
pyparrot/commandsandsensors/wifi.xml
pyparrot/images/__init__.py
pyparrot/networking/__init__.py
pyparrot/networking/bleConnection.py
pyparrot/networking/wifiConnection.py
pyparrot/scripts/__init__.py
pyparrot/scripts/findMinidrone.py
pyparrot/utils/NonBlockingStreamReader.py
pyparrot/utils/__init__.py
pyparrot/utils/bebop.sdp
pyparrot/utils/colorPrint.py
pyparrot/utils/vlc.py
pyparrot-1.5.20.dist-info/METADATA
pyparrot-1.5.20.dist-info/RECORD
pyparrot-1.5.20.dist-info/WHEEL
pyparrot-1.5.20.dist-info/entry_points.txt
pyparrot-1.5.20.dist-info/top_level.txt
