Metadata-Version: 2.1
Name: pyparrot
Version: 1.5.20
Summary: Python interface to control Parrot drones
Home-page: https://github.com/amymcgovern/pyparrot
Author: Amy McGovern
Author-email: dramymcgovern@gmail.com
License: UNKNOWN
Project-URL: Bug Reports, https://github.com/amymcgovern/pyparrot/issues
Project-URL: Funding, https://www.oufoundation.org/portal
Project-URL: Say Thanks!, https://saythanks.io/to/amymcgovern
Project-URL: Source, https://github.com/amymcgovern/pyparrot/
Keywords: python parrot drone education programming
Platform: UNKNOWN
Classifier: Development Status :: 4 - Beta
Classifier: Intended Audience :: Developers 
Classifier: Intended Audience :: Education
Classifier: Topic :: Education 
Classifier: Topic :: Software Development
Classifier: License :: OSI Approved :: MIT License
Classifier: Programming Language :: Python :: 3
Classifier: Programming Language :: Python :: 3.4
Classifier: Programming Language :: Python :: 3.5
Classifier: Programming Language :: Python :: 3.6
Requires-Python: >=3
